mustlink/__init__.py
mustlink/mustlink.py
mustlink-0.3.2.dist-info/LICENSE
mustlink-0.3.2.dist-info/METADATA
mustlink-0.3.2.dist-info/WHEEL
mustlink-0.3.2.dist-info/top_level.txt
mustlink-0.3.2.dist-info/RECORD
