Metadata-Version: 2.1
Name: mustlink
Version: 0.3.2
Summary: A python wrapper for the ESA mustlink API
Home-page: https://github.com/msbentley/mustlink
Download-URL: https://github.com/msbentley/mustlink/archive/0.3.2.tar.gz
Author: Mark S. Bentley
Author-email: mark@lunartech.org
Keywords: telemetry,MUST,ESA
Requires-Python: >=3.0
License-File: LICENSE
Requires-Dist: matplotlib
Requires-Dist: pandas
Requires-Dist: pyyaml
Requires-Dist: requests
Requires-Dist: pysocks
